sctuner/__init__.py
sctuner/models.py
sctuner/optimisers.py
sctuner/pqutils.py
sctuner/scalesc.py
sctuner/vae.py
sctuner-0.1.0.dist-info/METADATA
sctuner-0.1.0.dist-info/WHEEL
sctuner-0.1.0.dist-info/licenses/LICENSE
sctuner-0.1.0.dist-info/RECORD
